isplogger/__init__.py
isplogger/cmd_line.py
isplogger/isplogger.py
isplogger/logger.py
isplogger-0.2.1.dist-info/METADATA
isplogger-0.2.1.dist-info/RECORD
isplogger-0.2.1.dist-info/WHEEL
isplogger-0.2.1.dist-info/entry_points.txt
isplogger-0.2.1.dist-info/top_level.txt
