Metadata-Version: 2.1
Name: isplogger
Version: 0.2.1
Summary: A tool for monitoring/recording internet access
Home-page: http://github.com/tjkessler/isplogger
Author: Travis Kessler
Author-email: travis.j.kessler@gmail.com
License: MIT
Platform: UNKNOWN
